{
    "metadata": {
        "table_name": "schedules",
        "column_families": [
            "classrooms",
            "teachers"
        ],
        "disabled": false,
        "created": "2024-05-24T22:13:05.655623",
        "modified": "2024-05-24T22:13:05.655623",
        "versions": 3
    },
    "rows_data": {
        "31cdebc1-f432-4304-ab98-71614f2f58e0": {
            "classrooms": {
                "identifier": {
                    "2024-04-24T22:13:05.655623": "J-581",
                    "2024-05-09T22:13:05.655623": "A-622"
                },
                "capacity": {
                    "2024-05-04T22:13:05.655623": "20",
                    "2024-05-02T22:13:05.655623": "34"
                },
                "type": {
                    "2024-04-30T22:13:05.655623": "aula colaborativa",
                    "2024-05-10T22:13:05.655623": "salon",
                    "2024-05-19T22:13:05.655623": "salon"
                }
            },
            "teachers": {
                "name": {
                    "2024-05-19T22:13:05.655623": "Jordan Sims",
                    "2024-05-09T22:13:05.655623": "Marc Mullins"
                },
                "faculty": {
                    "2024-04-29T22:13:05.655623": "Design Innovations & Arts",
                    "2024-05-14T22:13:05.655623": "Arquitectura",
                    "2024-04-24T22:13:05.655623": "Arquitectura"
                }
            }
        },
        "99661b4e-7bb7-4091-8bf2-beeee0986ec8": {
            "classrooms": {
                "identifier": {
                    "2024-04-29T22:13:05.655623": "H-423"
                },
                "capacity": {
                    "2024-05-12T22:13:05.655623": "50"
                },
                "type": {
                    "2024-05-13T22:13:05.655623": "laboratorio",
                    "2024-05-19T22:13:05.655623": "salon",
                    "2024-04-25T22:13:05.655623": "laboratorio"
                }
            },
            "teachers": {
                "name": {
                    "2024-05-09T22:13:05.655623": "Dr. Travis Blake",
                    "2024-05-03T22:13:05.655623": "Robert Cox"
                },
                "faculty": {
                    "2024-04-28T22:13:05.655623": "Ingenieria",
                    "2024-05-20T22:13:05.655623": "Design Innovations & Arts"
                }
            }
        },
        "47ff3946-3fc3-4076-aa33-e9605a4a13ab": {
            "classrooms": {
                "identifier": {
                    "2024-05-09T22:13:05.655623": "C-674"
                },
                "capacity": {
                    "2024-05-15T22:13:05.655623": "24",
                    "2024-05-23T22:13:05.655623": "42",
                    "2024-05-24T22:13:05.655623": "37"
                },
                "type": {
                    "2024-05-17T22:13:05.655623": "laboratorio",
                    "2024-05-10T22:13:05.655623": "salon",
                    "2024-04-28T22:13:05.655623": "aula colaborativa"
                }
            },
            "teachers": {
                "name": {
                    "2024-05-21T22:13:05.655623": "Tabitha Kennedy"
                },
                "faculty": {
                    "2024-05-13T22:13:05.655623": "Ciencias Sociales"
                }
            }
        },
        "c4341889-4094-4da2-9b48-67c2f06676da": {
            "classrooms": {
                "identifier": {
                    "2024-05-06T22:13:05.655623": "J-468",
                    "2024-05-01T22:13:05.655623": "J-375",
                    "2024-05-08T22:13:05.655623": "A-599"
                },
                "capacity": {
                    "2024-05-21T22:13:05.655623": "26",
                    "2024-05-04T22:13:05.655623": "49"
                },
                "type": {
                    "2024-04-27T22:13:05.655623": "salon",
                    "2024-05-03T22:13:05.655623": "laboratorio",
                    "2024-05-18T22:13:05.655623": "laboratorio"
                }
            },
            "teachers": {
                "name": {
                    "2024-05-13T22:13:05.655623": "Katherine Hoffman",
                    "2024-04-26T22:13:05.655623": "Alfred Graves"
                },
                "faculty": {
                    "2024-05-12T22:13:05.657178": "Business and Management"
                }
            }
        },
        "c5ed5d25-7b0c-4425-8897-0676bb432e0a": {
            "classrooms": {
                "identifier": {
                    "2024-05-09T22:13:05.657178": "A-868",
                    "2024-04-24T22:13:05.657178": "C-892"
                },
                "capacity": {
                    "2024-04-27T22:13:05.657178": "35",
                    "2024-05-23T22:13:05.657178": "33",
                    "2024-05-12T22:13:05.657178": "28"
                },
                "type": {
                    "2024-05-01T22:13:05.657178": "laboratorio",
                    "2024-05-05T22:13:05.657178": "salon",
                    "2024-05-22T22:13:05.657178": "aula"
                }
            },
            "teachers": {
                "name": {
                    "2024-05-16T22:13:05.657178": "Collin Hayes"
                },
                "faculty": {
                    "2024-04-29T22:13:05.657178": "Arquitectura",
                    "2024-05-24T22:13:05.657178": "Ciencias Sociales"
                }
            }
        },
        "cd4f7314-0573-48ef-87da-0ebcac090af3": {
            "classrooms": {
                "identifier": {
                    "2024-05-18T22:13:05.657178": "H-215"
                },
                "capacity": {
                    "2024-04-26T22:13:05.657178": "43",
                    "2024-05-14T22:13:05.657178": "32"
                },
                "type": {
                    "2024-05-03T22:13:05.657178": "salon",
                    "2024-05-10T22:13:05.657178": "aula colaborativa"
                }
            },
            "teachers": {
                "name": {
                    "2024-05-18T22:13:05.657178": "Susan Adams"
                },
                "faculty": {
                    "2024-05-04T22:13:05.657178": "Ingenieria",
                    "2024-05-07T22:13:05.657178": "Ingenieria",
                    "2024-05-20T22:13:05.657178": "Ciencias y Humanidades"
                }
            }
        },
        "1930874d-b7e6-43b2-a5ae-f8b9efbba5d5": {
            "classrooms": {
                "identifier": {
                    "2024-05-01T22:13:05.657178": "CIT-624",
                    "2024-05-15T22:13:05.657178": "K-605"
                },
                "capacity": {
                    "2024-05-01T22:13:05.657178": "41",
                    "2024-05-20T22:13:05.657178": "41",
                    "2024-05-05T22:13:05.657178": "21"
                },
                "type": {
                    "2024-05-14T22:13:05.657178": "aula",
                    "2024-05-13T22:13:05.657178": "salon"
                }
            },
            "teachers": {
                "name": {
                    "2024-04-28T22:13:05.657178": "Mark Calhoun",
                    "2024-05-18T22:13:05.657178": "Christy Wood"
                },
                "faculty": {
                    "2024-05-16T22:13:05.657178": "Ciencias Sociales",
                    "2024-04-30T22:13:05.657178": "Design Innovations & Arts",
                    "2024-05-22T22:13:05.657178": "Ciencias y Humanidades"
                }
            }
        },
        "1670b2c5-6b3a-4f6f-bcc1-693b16bfcb25": {
            "classrooms": {
                "identifier": {
                    "2024-05-23T22:13:05.657178": "H-311",
                    "2024-04-26T22:13:05.657178": "G-895"
                },
                "capacity": {
                    "2024-05-02T22:13:05.657178": "47"
                },
                "type": {
                    "2024-05-02T22:13:05.657178": "aula",
                    "2024-04-29T22:13:05.657178": "salon",
                    "2024-04-26T22:13:05.657178": "aula colaborativa"
                }
            },
            "teachers": {
                "name": {
                    "2024-05-03T22:13:05.657178": "Michael Brown"
                },
                "faculty": {
                    "2024-05-09T22:13:05.658229": "Design Innovations & Arts",
                    "2024-05-23T22:13:05.658229": "Educacion",
                    "2024-05-24T22:13:05.658229": "Arquitectura"
                }
            }
        },
        "c9cb724e-0478-47af-941b-de711887a09f": {
            "classrooms": {
                "identifier": {
                    "2024-05-22T22:13:05.658229": "K-840",
                    "2024-05-18T22:13:05.658229": "I-823"
                },
                "capacity": {
                    "2024-04-29T22:13:05.658229": "28"
                },
                "type": {
                    "2024-05-20T22:13:05.658229": "salon",
                    "2024-05-22T22:13:05.658229": "salon",
                    "2024-05-07T22:13:05.658229": "aula colaborativa"
                }
            },
            "teachers": {
                "name": {
                    "2024-05-03T22:13:05.658229": "Lisa Brown"
                },
                "faculty": {
                    "2024-05-08T22:13:05.658229": "Ingenieria",
                    "2024-05-05T22:13:05.658229": "Ingenieria"
                }
            }
        },
        "f849dc73-5d89-4799-921c-5b8ca313f773": {
            "classrooms": {
                "identifier": {
                    "2024-05-04T22:13:05.658229": "CIT-207"
                },
                "capacity": {
                    "2024-05-07T22:13:05.658229": "34",
                    "2024-04-27T22:13:05.658229": "40",
                    "2024-04-24T22:13:05.658229": "40"
                },
                "type": {
                    "2024-05-04T22:13:05.658229": "salon",
                    "2024-04-28T22:13:05.658229": "aula",
                    "2024-05-08T22:13:05.658229": "salon"
                }
            },
            "teachers": {
                "name": {
                    "2024-05-22T22:13:05.658229": "Christy Duarte"
                },
                "faculty": {
                    "2024-05-10T22:13:05.658229": "Educacion"
                }
            }
        }
    }
}